flair/__init__.py
flair/class_utils.py
flair/data.py
flair/file_utils.py
flair/inference_utils.py
flair/optim.py
flair/py.typed
flair/samplers.py
flair/splitter.py
flair/tokenization.py
flair/training_utils.py
flair/datasets/__init__.py
flair/datasets/base.py
flair/datasets/biomedical.py
flair/datasets/document_classification.py
flair/datasets/entity_linking.py
flair/datasets/ocr.py
flair/datasets/relation_extraction.py
flair/datasets/sequence_labeling.py
flair/datasets/text_image.py
flair/datasets/text_text.py
flair/datasets/treebanks.py
flair/embeddings/__init__.py
flair/embeddings/base.py
flair/embeddings/document.py
flair/embeddings/image.py
flair/embeddings/legacy.py
flair/embeddings/token.py
flair/embeddings/transformer.py
flair/models/__init__.py
flair/models/clustering.py
flair/models/entity_linker_model.py
flair/models/entity_mention_linking.py
flair/models/language_model.py
flair/models/lemmatizer_model.py
flair/models/multitask_model.py
flair/models/pairwise_classification_model.py
flair/models/pairwise_regression_model.py
flair/models/pos_model.bin
flair/models/prefixed_tagger.py
flair/models/regexp_tagger.py
flair/models/relation_classifier_model.py
flair/models/relation_extractor_model.py
flair/models/sequence_tagger_model.py
flair/models/tars_model.py
flair/models/text_classification_model.py
flair/models/text_regression_model.py
flair/models/word_tagger_model.py
flair/models/sequence_tagger_utils/__init__.py
flair/models/sequence_tagger_utils/crf.py
flair/models/sequence_tagger_utils/viterbi.py
flair/nn/__init__.py
flair/nn/decoder.py
flair/nn/dropout.py
flair/nn/model.py
flair/nn/multitask.py
flair/nn/recurrent.py
flair/nn/distance/__init__.py
flair/nn/distance/cosine.py
flair/nn/distance/euclidean.py
flair/nn/distance/hyperbolic.py
flair/trainers/__init__.py
flair/trainers/language_model_trainer.py
flair/trainers/trainer.py
flair/trainers/plugins/__init__.py
flair/trainers/plugins/base.py
flair/trainers/plugins/metric_records.py
flair_pos-0.13.1.dist-info/METADATA
flair_pos-0.13.1.dist-info/WHEEL
flair_pos-0.13.1.dist-info/licenses/LICENSE
flair_pos-0.13.1.dist-info/RECORD
