Metadata-Version: 2.1
Name: flair-pos
Version: 0.13.1
Summary: A very simple framework for state-of-the-art NLP
Project-URL: Homepage, https://github.com/flairNLP/flair
Author-email: Alan Akbik <alan.akbik@gmail.com>
License-Expression: MIT
License-File: LICENSE
Requires-Python: >=3.8
Requires-Dist: bioc<3.0.0,>=2.0.0
Requires-Dist: boto3>=1.20.27
Requires-Dist: bpemb>=0.3.2
Requires-Dist: conllu>=4.0
Requires-Dist: deprecated>=1.2.13
Requires-Dist: ftfy>=6.1.0
Requires-Dist: gdown>=4.4.0
Requires-Dist: gensim>=4.2.0
Requires-Dist: huggingface-hub>=0.10.0
Requires-Dist: janome>=0.4.2
Requires-Dist: langdetect>=1.0.9
Requires-Dist: lxml>=4.8.0
Requires-Dist: matplotlib>=2.2.3
Requires-Dist: more-itertools>=8.13.0
Requires-Dist: mpld3>=0.3
Requires-Dist: pptree>=3.1
Requires-Dist: python-dateutil>=2.8.2
Requires-Dist: pytorch-revgrad>=0.2.0
Requires-Dist: regex>=2022.1.18
Requires-Dist: scikit-learn>=1.0.2
Requires-Dist: segtok>=1.5.11
Requires-Dist: semver<4.0.0,>=3.0.0
Requires-Dist: sqlitedict>=2.0.0
Requires-Dist: tabulate>=0.8.10
Requires-Dist: torch!=1.8,>=1.5.0
Requires-Dist: tqdm>=4.63.0
Requires-Dist: transformer-smaller-training-vocab>=0.2.3
Requires-Dist: transformers[sentencepiece]<5.0.0,>=4.18.0
Requires-Dist: urllib3<2.0.0,>=1.0.0
Requires-Dist: wikipedia-api>=0.5.7
